jpathpy/LICENSE
jpathpy/__init__.py
jpathpy/exceptions.py
jpathpy/jpath_funcs.py
jpathpy/lex.py
jpathpy/parse.py
jpathpy-2.0.0.dist-info/LICENSE
jpathpy-2.0.0.dist-info/METADATA
jpathpy-2.0.0.dist-info/WHEEL
jpathpy-2.0.0.dist-info/top_level.txt
jpathpy-2.0.0.dist-info/zip-safe
jpathpy-2.0.0.dist-info/RECORD
