Metadata-Version: 2.1
Name: jpathpy
Version: 2.0.0
Summary: JPath is easy way for selecting items from objects, that can be iterate by keys or indices (such as dictionaries or lists).
Home-page: https://github.com/vowatchka/jpathpy
Author: Vladimir Saltykov
Author-email: vowatchka@mail.ru
License: MIT
Keywords: jpathpy python jpath json syntax selection select
Platform: UNKNOWN
Classifier: Development Status :: 5 - Production/Stable
Classifier: Intended Audience :: Developers
Classifier: License :: OSI Approved :: MIT License
Classifier: Operating System :: OS Independent
Classifier: Programming Language :: Python :: 3
Classifier: Programming Language :: Python :: 3.5
Classifier: Programming Language :: Python :: 3.6
Classifier: Programming Language :: Python :: 3.7
Classifier: Programming Language :: Python :: 3.8
Classifier: Programming Language :: Python :: 3.9
Classifier: Topic :: Software Development :: Libraries :: Python Modules
Classifier: Topic :: Utilities
Requires-Dist: ply (<4,>=3.9)
